[
  {
    "userName": "AkshR",
    "password": "70012",
    "userId": "419483e7-b379-48af-a228-7fe6c39c3170"
  },
  {
    "userName": "Jimmy Johnson's",
    "password": "WQE98AXSWEQ",
    "userId": "86039d5e-2c4f-4403-a598-f61d4ddf8571"
  },
  {
    "userName": "Peter Parker",
    "password": "WQE98AQUIOTR123",
    "userId": "71ddd9e5-6df1-426d-a82a-7515551004d6"
  },
  {
    "userName": "Jimmy Parker",
    "password": "QWERTYUOP",
    "userId": "60475d71-15f6-48e8-abd4-847dd693bdac"
  },
  {
    "userName": "Billy James",
    "password": "QWERTYUOP",
    "userId": "fe559fb6-3208-4eec-aabe-3051bd0e8c05"
  },
  {
    "userName": "Maclinn",
    "password": "QWASQWAS",
    "userId": "90c632c1-8175-4a46-8f45-c0cd7c28f4ee"
  }
]
